midas/modules/blackstart/__init__.py
midas/modules/blackstart/module.py
midas/modules/blackstart/grids/__init__.py
midas/modules/blackstart/grids/blackstartgrid_moo_evaluation_grid.py
midas_blackstart-1.0.0a2.dist-info/LICENSE
midas_blackstart-1.0.0a2.dist-info/METADATA
midas_blackstart-1.0.0a2.dist-info/WHEEL
midas_blackstart-1.0.0a2.dist-info/top_level.txt
midas_blackstart-1.0.0a2.dist-info/RECORD
